lambda_cli/__init__.py
lambda_cli/api.py
lambda_cli/config.py
lambda_cli/main.py
lambda_labs_cli-0.1.0.dist-info/METADATA
lambda_labs_cli-0.1.0.dist-info/WHEEL
lambda_labs_cli-0.1.0.dist-info/entry_points.txt
lambda_labs_cli-0.1.0.dist-info/top_level.txt
lambda_labs_cli-0.1.0.dist-info/RECORD
