Metadata-Version: 2.4
Name: lambda-labs-cli
Version: 0.1.0
Summary: CLI tool for Lambda Labs Cloud
Requires-Python: >=3.11
Requires-Dist: typer[all]>=0.12.0
Requires-Dist: httpx>=0.27.0
Requires-Dist: rich>=13.7.0
